[
    {
        "id": 1,
        "user": "CS101",
        "email": "Computer Science 101",
        "password": "password123",
        "dateLogged": "2023-10-01"
    },
    {
        "id": 2,
        "user": "CS102",
        "email": "Computer Science 102",
        "password": "password123",
        "dateLogged": "2023-10-02"
    },
    {
        "id": 3,
        "user": "CS103",
        "email": "Computer Science 103",
        "password": "password123",
        "dateLogged": "2023-10-03"
    },
    {
        "id": 4,
        "user": "CS104",
        "email": "Computer Science 104",
        "password": "password123",
        "dateLogged": "2023-10-04"
    },
    {
        "id": 5,
        "user": "CS105",
        "email": "Computer Science 105",
        "password": "password123",
        "dateLogged": "2023-10-05"
    },
    {
        "id": 6,
        "user": "CS106",
        "email": "Computer Science 106",
        "password": "password123",
        "dateLogged": "2023-10-06"
    },
    {
        "id": 7,
        "user": "CS107",
        "email": "Computer Science 107",
        "password": "password123",
        "dateLogged": "2023-10-07"
    },
    {
        "id": 8,
        "user": "CS108",
        "email": "Computer Science 108",
        "password": "password123",
        "dateLogged": "2023-10-08"
    },
    {
        "id": 9,
        "user": "CS109",
        "email": "Computer Science 109",
        "password": "password123",
        "dateLogged": "2023-10-09"
    },
    {
        "id": 10,
        "user": "CS110",
        "email": "Computer Science 110",
        "password": "password123",
        "dateLogged": "2023-10-10"
    },
    {
        "id": 11,
        "user": "CS111",
        "email": "Computer Science 111",
        "password": "password123",
        "dateLogged": "2023-10-11"
    },
    {
        "id": 12,
        "user": "CS112",
        "email": "Computer Science 112",
        "password": "password123",
        "dateLogged": "2023-10-12"
    },
    {
        "id": 13,
        "user": "CS113",
        "email": "Computer Science 113",
        "password": "password123",
        "dateLogged": "2023-10-13"
    },
    {
        "id": 14,
        "user": "CS114",
        "email": "Computer Science 114",
        "password": "password123",
        "dateLogged": "2023-10-14"
    },
    {
        "id": 15,
        "user": "CS115",
        "email": "Computer Science 115",
        "password": "password321",
        "dateLogged": "2023-10-15"
    }

]
